{
  "doc_id": "pdf_098",
  "entries": [
    {
      "level": 1,
      "title": "Energy Science Division",
      "page": 1,
      "chunk_id": null
    },
    {
      "level": 1,
      "title": "UNIVERSITY A",
      "page": 1,
      "chunk_id": null
    },
    {
      "level": 1,
      "title": "Energy Science Division",
      "page": 1,
      "chunk_id": null
    },
    {
      "level": 1,
      "title": "University A",
      "page": 1,
      "chunk_id": null
    },
    {
      "level": 1,
      "title": "Executive Summary",
      "page": 1,
      "chunk_id": null
    },
    {
      "level": 1,
      "title": "The improvement in efficiency and restored capacity",
      "page": 1,
      "chunk_id": null
    },
    {
      "level": 1,
      "title": "gained directly at the unit was solely attributable to",
      "page": 1,
      "chunk_id": null
    },
    {
      "level": 1,
      "title": "the average combined tonnage produced increased",
      "page": 1,
      "chunk_id": null
    },
    {
      "level": 1,
      "title": "University A pilot supports the medical labs and management offices",
      "page": 1,
      "chunk_id": null
    },
    {
      "level": 1,
      "title": "image shows several of the certified digital instrumentation used to",
      "page": 1,
      "chunk_id": null
    },
    {
      "level": 1,
      "title": "Energy Science Division",
      "page": 1,
      "chunk_id": null
    },
    {
      "level": 1,
      "title": "Product Brief",
      "page": 1,
      "chunk_id": null
    },
    {
      "level": 1,
      "title": "Energy Science Division",
      "page": 1,
      "chunk_id": null
    },
    {
      "level": 1,
      "title": "BOUNDARY LAYER",
      "page": 1,
      "chunk_id": null
    },
    {
      "level": 1,
      "title": "OIL REMOVED",
      "page": 1,
      "chunk_id": null
    },
    {
      "level": 1,
      "title": "BEFORE TREATMENT",
      "page": 1,
      "chunk_id": null
    },
    {
      "level": 1,
      "title": "AFTER TREATMENT",
      "page": 1,
      "chunk_id": null
    },
    {
      "level": 1,
      "title": "Energy Science Division",
      "page": 1,
      "chunk_id": null
    },
    {
      "level": 1,
      "title": "Energy Science Division",
      "page": 1,
      "chunk_id": null
    },
    {
      "level": 1,
      "title": "A diagnostic examination of the pilot equipment was implemented to determine if the operational",
      "page": 1,
      "chunk_id": null
    }
  ]
}